setup.py
expressgit/__init__.py
expressgit/__main__.py
expressgit/hi.py
expressgit.egg-info/PKG-INFO
expressgit.egg-info/SOURCES.txt
expressgit.egg-info/dependency_links.txt
expressgit.egg-info/not-zip-safe
expressgit.egg-info/top_level.txt