Metadata-Version: 1.0
Name: expressgit
Version: 1.0
Summary: Private git system
Home-page: http://github.com/ex8
Author: Matt M
Author-email: matt@puroxy.org
License: UNKNOWN
Platform: UNKNOWN
